setup.py
trhub/__init__.py
trhub.egg-info/PKG-INFO
trhub.egg-info/SOURCES.txt
trhub.egg-info/dependency_links.txt
trhub.egg-info/requires.txt
trhub.egg-info/top_level.txt
trhub/data/__init__.py
trhub/data/history/__init__.py
trhub/data/market/__init__.py
trhub/data/quant/__init__.py
trhub/data/trade/__init__.py
trhub/format/__init__.py
trhub/utils/__init__.py
trhub/utils/mkdown.py
trhub/utils/myemail.py