Metadata-Version: 1.0
Name: trhub
Version: 2.0.0
Summary: 图灵数据中心
Home-page: UNKNOWN
Author: iamee
Author-email: admin@cavacn.com
License: MIT License
Keywords: 图灵,数据中心
Platform: any
